LICENSE
MANIFEST.in
README.text
setup.py
bin/rapydcss
rapydcss/SASStoSCSS.py
rapydcss/__init__.py
rapydcss.egg-info/PKG-INFO
rapydcss.egg-info/SOURCES.txt
rapydcss.egg-info/dependency_links.txt
rapydcss.egg-info/requires.txt
rapydcss.egg-info/top_level.txt