Metadata-Version: 1.0
Name: rapydcss
Version: 0.0.1
Summary: Python-based SASS Compiler
Home-page: http://www.pyjeon.com/rapydcss
Author: Alexander Tsepkov
Author-email: UNKNOWN
License: GNU GPL3
Platform: any
